{
    "object_name": "Музей физической культуры и спорта Министерства спорта и туризма Республики Беларусь",
    "object_id": 1325901716,
    "contact": [
        "+375173277622",
        "+375173277237",
        "+375172004966",
        "+375172260272",
        "+375172261033",
        "+375172260147",
        "+375172004682",
        "+375173271734",
        "+375173273031",
        "+375172260689",
        "+375173272511",
        "+375172202294",
        "+375173271069"
    ],
    "business_url": "mst.gov.by",
    "object_category": "Министерства, ведомства, государственные службы",
    "object_links": [
        "http://youtube.com/channel/UC2TopAPtfdR1W7PfVG14a2w",
        "https://facebook.com/mst.gov.by",
        "https://twitter.com/minsport_tur_rb",
        "https://www.instagram.com/belarus.travel/"
    ],
    "address": "ул. Кирова, 8, корп. 2",
    "work_time": {
        "Понедельник": "09:00 – 13:0014:00 – 18:00",
        "Вторник": "09:00 – 13:0014:00 – 18:00",
        "Среда": "09:00 – 13:0014:00 – 18:00",
        "Четверг": "09:00 – 13:0014:00 – 18:00",
        "Пятница": "09:00 – 13:0014:00 – 18:00",
        "Суббота": "Выходной",
        "Воскресенье": "Выходной"
    },
    "features": null,
    "rating": 3.5,
    "attendance": {},
    "number_of_votes": null,
    "number_of_review": 6,
    "similar_objects": [
        {
            "object_id": 1067367650,
            "object_name": "Министерство антимонопольного регулирования и торговли",
            "object_link": "https://yandex.by/maps/org/ministerstvo_antimonopolnogo_regulirovaniya_i_torgovli_rb/1067367650/"
        },
        {
            "object_id": 38551563785,
            "object_name": "Госпогранкомитет",
            "object_link": "https://yandex.by/maps/org/gosudarstvenny_pogranichny_komitet_respubliki_belarus/38551563785/"
        },
        {
            "object_id": 1328009918,
            "object_name": "Министерство по налогам и сборам Республики Беларусь",
            "object_link": "https://yandex.by/maps/org/ministerstvo_po_nalogam_i_sboram_respubliki_belarus/1328009918/"
        },
        {
            "object_id": 233771552729,
            "object_name": "Минздрав",
            "object_link": "https://yandex.by/maps/org/dsp_minzdrava_rb/233771552729/"
        },
        {
            "object_id": 1339855275,
            "object_name": "Министерство Сельского Хозяйства и Продовольствия Республики Беларусь",
            "object_link": "https://yandex.by/maps/org/ministerstvo_selskogo_khozyaystva_i_prodovolstviya_respubliki_belarus/1339855275/"
        },
        {
            "object_id": 1302918279,
            "object_name": "Министерство лесного хозяйства РБ",
            "object_link": "https://yandex.by/maps/org/ministerstvo_lesnogo_khozyaystva_rb/1302918279/"
        },
        {
            "object_id": 1057252551,
            "object_name": "Министерство образования",
            "object_link": "https://yandex.by/maps/org/ministerstvo_obrazovaniya_rb/1057252551/"
        },
        {
            "object_id": 1021780171,
            "object_name": "Министерство архитектуры и строительства РБ",
            "object_link": "https://yandex.by/maps/org/ministerstvo_arkhitektury_i_stroitelstva_rb/1021780171/"
        },
        {
            "object_id": 1730588329,
            "object_name": "Министерство юстиции РБ",
            "object_link": "https://yandex.by/maps/org/ministerstvo_yustitsii_rb/1730588329/"
        },
        {
            "object_id": 1064836286,
            "object_name": "МИД",
            "object_link": "https://yandex.by/maps/org/ministerstvo_inostrannykh_del_respubliki_belarus/1064836286/"
        }
    ],
    "reviews_info": {
        "type_reviews": {
            "вид из здания ": 2,
            "злая гардеробщица ": 1,
            "положительные впечатления ": 1,
            "вежливые сотрудники ": 1
        },
        "reviews": [
            {
                "author_name": "Maria Dovnar",
                "author_profession": 11,
                "date": "2020-03-27",
                "comment": "Первое, что хочется отметить- это потрясающий вид из здания. Мотивирует побродить по Минску. Второе, это вежливый и услужливый персонал, подсказали где конференц-зал, и даже провели. Остались только положительные впечатления.",
                "author_url": "https://reviews.yandex.ru/user/maradovnar",
                "rating": 5
            },
            {
                "author_name": "Мари",
                "author_profession": 10,
                "date": "2020-11-05",
                "comment": "Злая гардеробщица).... У которой обед важнее всех событий. Чтобы так все гардеробщицы работали, с установленным по графику обедом!",
                "author_url": "https://reviews.yandex.ru/user/4v8mp2737ck871j2qeqmeqt688",
                "rating": 4
            },
            {
                "author_name": "Андрей М.",
                "author_profession": 5,
                "date": "2020-04-14",
                "comment": "Красивое здание, вежливые сотрудники.",
                "author_url": "https://reviews.yandex.ru/user/35grnpdyqx8dewb3x3ucg6cdpm",
                "rating": 5
            },
            {
                "author_name": "silic",
                "author_profession": 13,
                "date": "2020-09-20",
                "comment": "До сих пор не вышли из СССР",
                "author_url": "https://reviews.yandex.ru/user/g8mvj1fbmu4xd2e1bzzxwd82v0",
                "rating": 2
            },
            {
                "author_name": "Саша",
                "author_profession": 8,
                "date": "2020-07-19",
                "comment": "Пресс-служба быстро решает вопросы.",
                "author_url": "",
                "rating": 5
            },
            {
                "author_name": "Алексей Шабура",
                "author_profession": 3,
                "date": "2020-02-25",
                "comment": "Ок ок",
                "author_url": "https://reviews.yandex.ru/user/749zgt7m4vmh582vw4fwm642dr",
                "rating": 5
            }
        ]
    }
}